backports/hook_compressed.py
backports.hook_compressed-1.1.1.dist-info/LICENSE
backports.hook_compressed-1.1.1.dist-info/METADATA
backports.hook_compressed-1.1.1.dist-info/WHEEL
backports.hook_compressed-1.1.1.dist-info/top_level.txt
backports.hook_compressed-1.1.1.dist-info/RECORD
