Metadata-Version: 2.1
Name: backports.hook_compressed
Version: 1.1.1
Summary: Backport of fileinput.hook_compressed from Python 3.10
Author-email: "Jason R. Coombs" <jaraco@jaraco.com>
Project-URL: Source, https://github.com/jaraco/backports.hook_compressed
Classifier: Development Status :: 5 - Production/Stable
Classifier: Intended Audience :: Developers
Classifier: License :: OSI Approved :: MIT License
Classifier: Programming Language :: Python :: 3
Classifier: Programming Language :: Python :: 3 :: Only
Requires-Python: >=3.8
License-File: LICENSE
Provides-Extra: check
Requires-Dist: pytest-checkdocs >=2.4 ; extra == 'check'
Requires-Dist: pytest-ruff >=0.2.1 ; (sys_platform != "cygwin") and extra == 'check'
Provides-Extra: cover
Requires-Dist: pytest-cov ; extra == 'cover'
Provides-Extra: doc
Requires-Dist: sphinx >=3.5 ; extra == 'doc'
Requires-Dist: jaraco.packaging >=9.3 ; extra == 'doc'
Requires-Dist: rst.linker >=1.9 ; extra == 'doc'
Requires-Dist: furo ; extra == 'doc'
Requires-Dist: sphinx-lint ; extra == 'doc'
Provides-Extra: enabler
Requires-Dist: pytest-enabler >=2.2 ; extra == 'enabler'
Provides-Extra: test
Requires-Dist: pytest !=8.1.*,>=6 ; extra == 'test'
Provides-Extra: type
Requires-Dist: pytest-mypy ; extra == 'type'
